{
  "id": 1,
  "projectId": 1,
  "title": "《街篮2》反馈分析报告（AI 生成 · 多渠道）",
  "periodStart": "2024-06-01",
  "periodEnd": "2026-04-21",
  "totalFeedback": 842,
  "avgScore": 38.3,
  "sourceDistribution": {
    "questionnaire": 499,
    "appstore": 196,
    "taptap": 147
  },
  "categoryDistribution": {
    "美术表现": 116,
    "操作手感": 147,
    "设备兼容": 7,
    "整体体验": 124,
    "战斗体验": 125,
    "综合体验": 184,
    "游戏平衡": 118,
    "玩法设计": 12,
    "性能问题": 9
  },
  "sentimentDistribution": {
    "negative": 280,
    "neutral": 290,
    "positive": 272
  },
  "urgencyDistribution": {
    "critical": 179,
    "medium": 251,
    "low": 191,
    "high": 96,
    "normal": 125
  },
  "topKeywords": [
    "安卓手机",
    "网络延迟",
    "氪金",
    "华为",
    "小米",
    "匹配",
    "模拟器",
    "画面",
    "中锋",
    "vivo",
    "得分后卫",
    "技能",
    "充值",
    "平衡",
    "手感",
    "操作",
    "三星",
    "大前锋",
    "小前锋",
    "网络"
  ],
  "scoreRanges": {
    "0-20": 234,
    "21-40": 96,
    "41-60": 408,
    "61-80": 95,
    "81-100": 9
  },
  "categoryAvgScores": [
    {
      "category": "综合体验",
      "avgScore": 2.1956521739130435,
      "count": 184
    },
    {
      "category": "游戏平衡",
      "avgScore": 41.66949152542373,
      "count": 118
    },
    {
      "category": "玩法设计",
      "avgScore": 43.25,
      "count": 12
    },
    {
      "category": "美术表现",
      "avgScore": 45.96551724137931,
      "count": 116
    },
    {
      "category": "整体体验",
      "avgScore": 47.74193548387097,
      "count": 124
    },
    {
      "category": "操作手感",
      "avgScore": 48.17006802721088,
      "count": 147
    },
    {
      "category": "设备兼容",
      "avgScore": 49.42857142857143,
      "count": 7
    },
    {
      "category": "战斗体验",
      "avgScore": 54.552,
      "count": 125
    },
    {
      "category": "性能问题",
      "avgScore": 100,
      "count": 9
    }
  ],
  "sentimentAvgScores": [
    {
      "sentiment": "negative",
      "avgScore": 17.357142857142858,
      "count": 280
    },
    {
      "sentiment": "neutral",
      "avgScore": 47.141379310344824,
      "count": 290
    },
    {
      "sentiment": "positive",
      "avgScore": 50.393382352941174,
      "count": 272
    }
  ],
  "urgentIssues": 275,
  "lowScoreFeedback": [
    {
      "id": "appstore_1096974019_1_0",
      "source": "appstore",
      "content": "靠还我账号 好久没登，tm直接换服务商了。之前的老账号直接清除了。",
      "category": "综合体验",
      "sentiment": "negative",
      "urgency": "critical",
      "keywords": [],
      "score": 1,
      "timestamp": "2026-04-21T09:12:02.056Z",
      "author": "afeizhz",
      "version": "1.50.4"
    },
    {
      "id": "appstore_1096974019_1_1",
      "source": "appstore",
      "content": "充钱 充钱就厉害",
      "category": "综合体验",
      "sentiment": "negative",
      "urgency": "critical",
      "keywords": [],
      "score": 1,
      "timestamp": "2026-04-21T09:12:02.056Z",
      "author": "🙈😔😊",
      "version": "1.50.4"
    },
    {
      "id": "appstore_1096974019_1_2",
      "source": "appstore",
      "content": "登陆 突然登不了了",
      "category": "综合体验",
      "sentiment": "negative",
      "urgency": "critical",
      "keywords": [],
      "score": 1,
      "timestamp": "2026-04-21T09:12:02.056Z",
      "author": "Hfcgddfhjnbvg",
      "version": "1.50.4"
    },
    {
      "id": "appstore_1096974019_1_4",
      "source": "appstore",
      "content": "垃圾 垃圾，投半天不进一个球",
      "category": "综合体验",
      "sentiment": "negative",
      "urgency": "critical",
      "keywords": [],
      "score": 1,
      "timestamp": "2026-04-21T09:12:02.056Z",
      "author": "sjshgxvsus",
      "version": "1.50.4"
    },
    {
      "id": "appstore_1096974019_1_5",
      "source": "appstore",
      "content": "0星，我账号呢？ 我问你，我的账号呢？一年多没上，账号没了？",
      "category": "综合体验",
      "sentiment": "negative",
      "urgency": "critical",
      "keywords": [],
      "score": 1,
      "timestamp": "2026-04-21T09:12:02.056Z",
      "author": "下周新声音这配置",
      "version": "1.50.4"
    },
    {
      "id": "appstore_1096974019_1_6",
      "source": "appstore",
      "content": "骗子游戏 冲了几万块钱，退游两年左右回来账号没了。也没法找回。官方群都进不去。无敌了",
      "category": "综合体验",
      "sentiment": "negative",
      "urgency": "critical",
      "keywords": [],
      "score": 1,
      "timestamp": "2026-04-21T09:12:02.056Z",
      "author": "jxoakskkdisja",
      "version": "1.50.4"
    },
    {
      "id": "appstore_1096974019_1_7",
      "source": "appstore",
      "content": "垃圾垃圾 垃圾游戏，腊鸡匹配机制，充钱的在里面横着走，没充钱的永远打得都是充钱的，充钱永远都是开挂机制，垃圾垃圾，赶紧下架吧，怪不得没人玩",
      "category": "综合体验",
      "sentiment": "negative",
      "urgency": "critical",
      "keywords": [
        "匹配"
      ],
      "score": 1,
      "timestamp": "2026-04-21T09:12:02.056Z",
      "author": "腊鸡腊鸡，永远的腊鸡",
      "version": "1.50.4"
    },
    {
      "id": "appstore_1096974019_1_8",
      "source": "appstore",
      "content": "一星都嫌多，劝退新人 这款垃圾游戏，新人没资源，老人氪金也没用，游戏没有检测外挂的系统，全靠录屏提交肉眼分辨，段位上去基本全是开挂的而且有些开挂的好像有人脉一样不会被封号，长期霸榜，游戏体验差环境严重不平衡，建议新人不要入坑！！！",
      "category": "游戏平衡",
      "sentiment": "negative",
      "urgency": "critical",
      "keywords": [
        "平衡"
      ],
      "score": 1,
      "timestamp": "2026-04-21T09:12:02.056Z",
      "author": "宝宝肚肚打雷辣",
      "version": "1.50.4"
    },
    {
      "id": "appstore_1096974019_1_10",
      "source": "appstore",
      "content": "把之前的号还给我！！！！ 是不是又骗人啊？",
      "category": "综合体验",
      "sentiment": "negative",
      "urgency": "critical",
      "keywords": [],
      "score": 1,
      "timestamp": "2026-04-21T09:12:02.056Z",
      "author": "zhangwenyu111",
      "version": "1.50.4"
    },
    {
      "id": "appstore_1096974019_1_11",
      "source": "appstore",
      "content": "非常一般 感觉这个游戏设计跟半成品一样，按键反馈怪怪的，篮板、盖帽跟迷一样，老是跟着常理感觉反着来，特别恶心想吐，匹配时间较长，还有进入游戏前要等2s画面是啥意思，感觉非常奇葩。",
      "category": "美术表现",
      "sentiment": "negative",
      "urgency": "critical",
      "keywords": [
        "画面",
        "匹配"
      ],
      "score": 1,
      "timestamp": "2026-04-21T09:12:02.056Z",
      "author": "不让不让动",
      "version": "1.50.4"
    }
  ],
  "highScoreFeedback": [
    {
      "id": "taptap_175459_3_29",
      "source": "taptap",
      "content": "之前写过一次评价，但是没写到一些重点上，现在有点闲空，把之前的删掉，重新写一写，这游戏为什么给一星。\\\\\n\\\\\n首先感官最差的就是球员的培养，所有球员都需要以下东西\\\\\n\\\\\n1.等级-能量饮料（经验卡）\\\\\n\\\\\n这个没的说，养成必不可少的东西，各类养成的游戏都会有。\\\\\n\\\\\n2.球员技能进阶-通用进阶卡以及球员专属进阶卡\\\\\n\\\\\n通用技能卡的免费来源目前只有三种，第一种活跃礼包每天16张，以及商城15活跃币可以买一张，每天限量20张；第二种活动会给一点，记住，是一点；第三种是天梯对局中，评分10分以上会给一到两张。剩下的氪金方式一个是冠军手册给一点，200级平均一级给一个；剩下就是氪金约等于一块钱一张。\\\\\n\\\\\n所以球员的小技能进阶有45个由于每个进阶需要的数字有所不同，现在往小了说，平均需要十五张，四十五个共需要差不多675张通用进阶卡。（这个数字只会比这更高）\\\\\n\\\\\n球员专属进阶卡，每个球员都有九个需要专属进阶卡来进阶，每次需要12张，共102张。免费获得的方式只有在每日活跃宝箱里产生24个，初始的三位球员便宜一点4个碎屏换一张，其他普通球员七个换一张，花球球员12块",
      "category": "性能问题",
      "sentiment": "positive",
      "urgency": "low",
      "keywords": [
        "卡顿",
        "网络",
        "职业",
        "操作",
        "画面"
      ],
      "score": 100,
      "timestamp": "2020-10-01T00:00:00.000Z",
      "author": "",
      "version": ""
    },
    {
      "id": "taptap_175459_4_38",
      "source": "taptap",
      "content": "之前写过一次评价，但是没写到一些重点上，现在有点闲空，把之前的删掉，重新写一写，这游戏为什么给一星。\\\\\n\\\\\n首先感官最差的就是球员的培养，所有球员都需要以下东西\\\\\n\\\\\n1.等级-能量饮料（经验卡）\\\\\n\\\\\n这个没的说，养成必不可少的东西，各类养成的游戏都会有。\\\\\n\\\\\n2.球员技能进阶-通用进阶卡以及球员专属进阶卡\\\\\n\\\\\n通用技能卡的免费来源目前只有三种，第一种活跃礼包每天16张，以及商城15活跃币可以买一张，每天限量20张；第二种活动会给一点，记住，是一点；第三种是天梯对局中，评分10分以上会给一到两张。剩下的氪金方式一个是冠军手册给一点，200级平均一级给一个；剩下就是氪金约等于一块钱一张。\\\\\n\\\\\n所以球员的小技能进阶有45个由于每个进阶需要的数字有所不同，现在往小了说，平均需要十五张，四十五个共需要差不多675张通用进阶卡。（这个数字只会比这更高）\\\\\n\\\\\n球员专属进阶卡，每个球员都有九个需要专属进阶卡来进阶，每次需要12张，共102张。免费获得的方式只有在每日活跃宝箱里产生24个，初始的三位球员便宜一点4个碎屏换一张，其他普通球员七个换一张，花球球员12块",
      "category": "性能问题",
      "sentiment": "positive",
      "urgency": "low",
      "keywords": [
        "卡顿",
        "网络",
        "职业",
        "操作",
        "画面"
      ],
      "score": 100,
      "timestamp": "2020-09-01T00:00:00.000Z",
      "author": "",
      "version": ""
    },
    {
      "id": "taptap_175459_5_47",
      "source": "taptap",
      "content": "之前写过一次评价，但是没写到一些重点上，现在有点闲空，把之前的删掉，重新写一写，这游戏为什么给一星。\\\\\n\\\\\n首先感官最差的就是球员的培养，所有球员都需要以下东西\\\\\n\\\\\n1.等级-能量饮料（经验卡）\\\\\n\\\\\n这个没的说，养成必不可少的东西，各类养成的游戏都会有。\\\\\n\\\\\n2.球员技能进阶-通用进阶卡以及球员专属进阶卡\\\\\n\\\\\n通用技能卡的免费来源目前只有三种，第一种活跃礼包每天16张，以及商城15活跃币可以买一张，每天限量20张；第二种活动会给一点，记住，是一点；第三种是天梯对局中，评分10分以上会给一到两张。剩下的氪金方式一个是冠军手册给一点，200级平均一级给一个；剩下就是氪金约等于一块钱一张。\\\\\n\\\\\n所以球员的小技能进阶有45个由于每个进阶需要的数字有所不同，现在往小了说，平均需要十五张，四十五个共需要差不多675张通用进阶卡。（这个数字只会比这更高）\\\\\n\\\\\n球员专属进阶卡，每个球员都有九个需要专属进阶卡来进阶，每次需要12张，共102张。免费获得的方式只有在每日活跃宝箱里产生24个，初始的三位球员便宜一点4个碎屏换一张，其他普通球员七个换一张，花球球员12块",
      "category": "性能问题",
      "sentiment": "positive",
      "urgency": "low",
      "keywords": [
        "卡顿",
        "网络",
        "职业",
        "操作",
        "画面"
      ],
      "score": 100,
      "timestamp": "2026-03-06T00:00:00.000Z",
      "author": "",
      "version": ""
    },
    {
      "id": "taptap_175459_3_29",
      "source": "taptap",
      "content": "之前写过一次评价，但是没写到一些重点上，现在有点闲空，把之前的删掉，重新写一写，这游戏为什么给一星。\\\\\n\\\\\n首先感官最差的就是球员的培养，所有球员都需要以下东西\\\\\n\\\\\n1.等级-能量饮料（经验卡）\\\\\n\\\\\n这个没的说，养成必不可少的东西，各类养成的游戏都会有。\\\\\n\\\\\n2.球员技能进阶-通用进阶卡以及球员专属进阶卡\\\\\n\\\\\n通用技能卡的免费来源目前只有三种，第一种活跃礼包每天16张，以及商城15活跃币可以买一张，每天限量20张；第二种活动会给一点，记住，是一点；第三种是天梯对局中，评分10分以上会给一到两张。剩下的氪金方式一个是冠军手册给一点，200级平均一级给一个；剩下就是氪金约等于一块钱一张。\\\\\n\\\\\n所以球员的小技能进阶有45个由于每个进阶需要的数字有所不同，现在往小了说，平均需要十五张，四十五个共需要差不多675张通用进阶卡。（这个数字只会比这更高）\\\\\n\\\\\n球员专属进阶卡，每个球员都有九个需要专属进阶卡来进阶，每次需要12张，共102张。免费获得的方式只有在每日活跃宝箱里产生24个，初始的三位球员便宜一点4个碎屏换一张，其他普通球员七个换一张，花球球员12块",
      "category": "性能问题",
      "sentiment": "positive",
      "urgency": "low",
      "keywords": [
        "卡顿",
        "网络",
        "职业",
        "操作",
        "画面"
      ],
      "score": 100,
      "timestamp": "2020-10-01T00:00:00.000Z",
      "author": "",
      "version": ""
    },
    {
      "id": "taptap_175459_4_38",
      "source": "taptap",
      "content": "之前写过一次评价，但是没写到一些重点上，现在有点闲空，把之前的删掉，重新写一写，这游戏为什么给一星。\\\\\n\\\\\n首先感官最差的就是球员的培养，所有球员都需要以下东西\\\\\n\\\\\n1.等级-能量饮料（经验卡）\\\\\n\\\\\n这个没的说，养成必不可少的东西，各类养成的游戏都会有。\\\\\n\\\\\n2.球员技能进阶-通用进阶卡以及球员专属进阶卡\\\\\n\\\\\n通用技能卡的免费来源目前只有三种，第一种活跃礼包每天16张，以及商城15活跃币可以买一张，每天限量20张；第二种活动会给一点，记住，是一点；第三种是天梯对局中，评分10分以上会给一到两张。剩下的氪金方式一个是冠军手册给一点，200级平均一级给一个；剩下就是氪金约等于一块钱一张。\\\\\n\\\\\n所以球员的小技能进阶有45个由于每个进阶需要的数字有所不同，现在往小了说，平均需要十五张，四十五个共需要差不多675张通用进阶卡。（这个数字只会比这更高）\\\\\n\\\\\n球员专属进阶卡，每个球员都有九个需要专属进阶卡来进阶，每次需要12张，共102张。免费获得的方式只有在每日活跃宝箱里产生24个，初始的三位球员便宜一点4个碎屏换一张，其他普通球员七个换一张，花球球员12块",
      "category": "性能问题",
      "sentiment": "positive",
      "urgency": "low",
      "keywords": [
        "卡顿",
        "网络",
        "职业",
        "操作",
        "画面"
      ],
      "score": 100,
      "timestamp": "2020-09-01T00:00:00.000Z",
      "author": "",
      "version": ""
    },
    {
      "id": "taptap_175459_5_47",
      "source": "taptap",
      "content": "之前写过一次评价，但是没写到一些重点上，现在有点闲空，把之前的删掉，重新写一写，这游戏为什么给一星。\\\\\n\\\\\n首先感官最差的就是球员的培养，所有球员都需要以下东西\\\\\n\\\\\n1.等级-能量饮料（经验卡）\\\\\n\\\\\n这个没的说，养成必不可少的东西，各类养成的游戏都会有。\\\\\n\\\\\n2.球员技能进阶-通用进阶卡以及球员专属进阶卡\\\\\n\\\\\n通用技能卡的免费来源目前只有三种，第一种活跃礼包每天16张，以及商城15活跃币可以买一张，每天限量20张；第二种活动会给一点，记住，是一点；第三种是天梯对局中，评分10分以上会给一到两张。剩下的氪金方式一个是冠军手册给一点，200级平均一级给一个；剩下就是氪金约等于一块钱一张。\\\\\n\\\\\n所以球员的小技能进阶有45个由于每个进阶需要的数字有所不同，现在往小了说，平均需要十五张，四十五个共需要差不多675张通用进阶卡。（这个数字只会比这更高）\\\\\n\\\\\n球员专属进阶卡，每个球员都有九个需要专属进阶卡来进阶，每次需要12张，共102张。免费获得的方式只有在每日活跃宝箱里产生24个，初始的三位球员便宜一点4个碎屏换一张，其他普通球员七个换一张，花球球员12块",
      "category": "性能问题",
      "sentiment": "positive",
      "urgency": "low",
      "keywords": [
        "卡顿",
        "网络",
        "职业",
        "操作",
        "画面"
      ],
      "score": 100,
      "timestamp": "2026-03-06T00:00:00.000Z",
      "author": "",
      "version": ""
    },
    {
      "id": "taptap_175459_3_29",
      "source": "taptap",
      "content": "之前写过一次评价，但是没写到一些重点上，现在有点闲空，把之前的删掉，重新写一写，这游戏为什么给一星。\\\\\n\\\\\n首先感官最差的就是球员的培养，所有球员都需要以下东西\\\\\n\\\\\n1.等级-能量饮料（经验卡）\\\\\n\\\\\n这个没的说，养成必不可少的东西，各类养成的游戏都会有。\\\\\n\\\\\n2.球员技能进阶-通用进阶卡以及球员专属进阶卡\\\\\n\\\\\n通用技能卡的免费来源目前只有三种，第一种活跃礼包每天16张，以及商城15活跃币可以买一张，每天限量20张；第二种活动会给一点，记住，是一点；第三种是天梯对局中，评分10分以上会给一到两张。剩下的氪金方式一个是冠军手册给一点，200级平均一级给一个；剩下就是氪金约等于一块钱一张。\\\\\n\\\\\n所以球员的小技能进阶有45个由于每个进阶需要的数字有所不同，现在往小了说，平均需要十五张，四十五个共需要差不多675张通用进阶卡。（这个数字只会比这更高）\\\\\n\\\\\n球员专属进阶卡，每个球员都有九个需要专属进阶卡来进阶，每次需要12张，共102张。免费获得的方式只有在每日活跃宝箱里产生24个，初始的三位球员便宜一点4个碎屏换一张，其他普通球员七个换一张，花球球员12块",
      "category": "性能问题",
      "sentiment": "positive",
      "urgency": "low",
      "keywords": [
        "卡顿",
        "网络",
        "职业",
        "操作",
        "画面"
      ],
      "score": 100,
      "timestamp": "2020-10-01T00:00:00.000Z",
      "author": "",
      "version": ""
    },
    {
      "id": "taptap_175459_4_38",
      "source": "taptap",
      "content": "之前写过一次评价，但是没写到一些重点上，现在有点闲空，把之前的删掉，重新写一写，这游戏为什么给一星。\\\\\n\\\\\n首先感官最差的就是球员的培养，所有球员都需要以下东西\\\\\n\\\\\n1.等级-能量饮料（经验卡）\\\\\n\\\\\n这个没的说，养成必不可少的东西，各类养成的游戏都会有。\\\\\n\\\\\n2.球员技能进阶-通用进阶卡以及球员专属进阶卡\\\\\n\\\\\n通用技能卡的免费来源目前只有三种，第一种活跃礼包每天16张，以及商城15活跃币可以买一张，每天限量20张；第二种活动会给一点，记住，是一点；第三种是天梯对局中，评分10分以上会给一到两张。剩下的氪金方式一个是冠军手册给一点，200级平均一级给一个；剩下就是氪金约等于一块钱一张。\\\\\n\\\\\n所以球员的小技能进阶有45个由于每个进阶需要的数字有所不同，现在往小了说，平均需要十五张，四十五个共需要差不多675张通用进阶卡。（这个数字只会比这更高）\\\\\n\\\\\n球员专属进阶卡，每个球员都有九个需要专属进阶卡来进阶，每次需要12张，共102张。免费获得的方式只有在每日活跃宝箱里产生24个，初始的三位球员便宜一点4个碎屏换一张，其他普通球员七个换一张，花球球员12块",
      "category": "性能问题",
      "sentiment": "positive",
      "urgency": "low",
      "keywords": [
        "卡顿",
        "网络",
        "职业",
        "操作",
        "画面"
      ],
      "score": 100,
      "timestamp": "2020-09-01T00:00:00.000Z",
      "author": "",
      "version": ""
    },
    {
      "id": "taptap_175459_5_47",
      "source": "taptap",
      "content": "之前写过一次评价，但是没写到一些重点上，现在有点闲空，把之前的删掉，重新写一写，这游戏为什么给一星。\\\\\n\\\\\n首先感官最差的就是球员的培养，所有球员都需要以下东西\\\\\n\\\\\n1.等级-能量饮料（经验卡）\\\\\n\\\\\n这个没的说，养成必不可少的东西，各类养成的游戏都会有。\\\\\n\\\\\n2.球员技能进阶-通用进阶卡以及球员专属进阶卡\\\\\n\\\\\n通用技能卡的免费来源目前只有三种，第一种活跃礼包每天16张，以及商城15活跃币可以买一张，每天限量20张；第二种活动会给一点，记住，是一点；第三种是天梯对局中，评分10分以上会给一到两张。剩下的氪金方式一个是冠军手册给一点，200级平均一级给一个；剩下就是氪金约等于一块钱一张。\\\\\n\\\\\n所以球员的小技能进阶有45个由于每个进阶需要的数字有所不同，现在往小了说，平均需要十五张，四十五个共需要差不多675张通用进阶卡。（这个数字只会比这更高）\\\\\n\\\\\n球员专属进阶卡，每个球员都有九个需要专属进阶卡来进阶，每次需要12张，共102张。免费获得的方式只有在每日活跃宝箱里产生24个，初始的三位球员便宜一点4个碎屏换一张，其他普通球员七个换一张，花球球员12块",
      "category": "性能问题",
      "sentiment": "positive",
      "urgency": "low",
      "keywords": [
        "卡顿",
        "网络",
        "职业",
        "操作",
        "画面"
      ],
      "score": 100,
      "timestamp": "2026-03-06T00:00:00.000Z",
      "author": "",
      "version": ""
    },
    {
      "id": "fb_b2_50",
      "source": "questionnaire",
      "content": "最多玩职业:中锋（C） | 篮球手游段位:王者 | 延迟感受:感觉没法玩了 | 接受匹配延长:不能接受 | 爆发提示明显度:5.0 | 爆发区域明显度:5.0 | 篮板碎裂动画:5.0 | 入场庆祝动作:5.0",
      "category": "战斗体验",
      "sentiment": "positive",
      "urgency": "normal",
      "keywords": [
        "中锋"
      ],
      "score": 80,
      "timestamp": "2024-06-02T10:00:00Z",
      "author": "",
      "version": ""
    }
  ],
  "content": "# 《游戏试玩反馈数据分析报告》\n\n## 1. 整体概况\n- **样本总量**：842份\n- **数据来源**：问卷（499份）、App Store（196份）、TapTap（147份）\n- **平均评分**：**38.3 / 100**（整体评价较差）\n- **情感倾向**：负面评价占比 **33.3%**（280份），中性评价 **34.4%**（290份），正面评价 **32.3%**（272份）。\n- **紧急问题**：标记为“critical”和“high”的紧急问题共计 **275个**，占总样本的 **32.7%**，表明存在大量亟待解决的严重问题。\n\n## 2. 评分分布分析\n| 分数段 | 样本数 | 占比 | 解读 |\n| :--- | :--- | :--- | :--- |\n| 0-20 | 234 | 27.8% | **极度不满群体**，体验存在根本性问题。 |\n| 21-40 | 96 | 11.4% | **强烈不满群体**，核心体验未达预期。 |\n| 41-60 | 408 | 48.5% | **主体评价区间**，体验有明显缺陷但尚有可取之处。 |\n| 61-80 | 95 | 11.3% | **基本满意群体**，体验达到及格线。 |\n| 81-100 | 9 | 1.1% | **高度满意群体**，样本极少，参考价值有限。 |\n\n**解读**：超过 **39.2%** 的玩家给出了40分以下的差评，而仅有 **12.4%** 的玩家给出60分以上的评价。评分呈现“中间多、两头少，但低分段比例畸高”的形态，整体口碑严峻。\n\n## 3. 各维度体验分析\n（按平均分从低到高排列，分数范围0-100）\n\n| 维度 | 平均分 | 样本数 | 分析 |\n| :--- | :--- | :--- | :--- |\n| **综合体验** | **2.2** | 184 | **灾难性短板**。分数极低，表明玩家在账号、服务、整体感受上存在普遍且强烈的不满。 |\n| 游戏平衡 | 41.7 | 118 | **主要短板**。玩家对角色、数值、付费带来的公平性质疑较大。 |\n| 玩法设计 | 43.3 | 12 | **主要短板**。样本少但分数低，需结合关键词分析具体玩法问题。 |\n| 美术表现 | 46.0 | 116 | **中等偏下**。画面、角色设计等未获得广泛认可。 |\n| 整体体验 | 47.7 | 124 | **中等偏下**。综合感受未达及格线。 |\n| 操作手感 | 48.2 | 147 | **中等偏下**。操控流畅度、反馈感有待优化。 |\n| 设备兼容 | 49.4 | 7 | **中等**。样本极少，但分数不高，需关注兼容性问题。 |\n| 战斗体验 | 54.6 | 125 | **相对优势项**。核心玩法过程中的体验相对最好，是游戏的潜在亮点。 |\n| 性能问题 | 100.0 | 9 | **样本偏差**。分数异常高且样本极少，可能为特定情况下的正面反馈，参考价值低。 |\n\n**结论**：游戏的**综合体验**是致命弱点，**游戏平衡**和**玩法设计**是核心痛点。**战斗体验**是目前相对最受认可的部分。\n\n## 4. 情感分析\n- **负面评价 (33.3%)**：情绪激烈，多集中于账号丢失、网络问题、平衡性差、逼氪等“硬伤”，用词如“垃圾”、“坑钱”、“卸载”。\n- **中性评价 (34.4%)**：多为客观描述问题或提出建议，如“网络延迟高”、“匹配时间长”、“安卓XX机型卡顿”。\n- **正面评价 (32.3%)**：主要集中在对篮球题材、部分角色设计、或战斗操作瞬间的认可，但常伴随对其他方面的批评。\n\n**特征**：负面与中性评价合计占比 **67.7%**，构成了玩家反馈的主体，表明游戏当前版本存在广泛且亟待解决的体验问题。\n\n## 5. 热门关键词解读 (TOP10)\n1.  **安卓手机 (309次)**：**设备兼容性**是首要关注点，玩家频繁提及具体机型。\n2.  **网络延迟 (254次)**：**网络优化**是核心痛点，严重影响实时对战体验。\n3.  **氪金 (96次)**：**付费设计**引发强烈关注，与“平衡”、“手感”等词关联，指向“付费致强”的负面感知。\n4.  **华为 (93次) / 5. 小米 (88次) / 10. vivo (39次)**：具体品牌机型被高频提及，坐实了安卓端，特别是国产主流品牌的**兼容性与性能问题**。\n5.  **匹配 (57次)**：指向**匹配机制**（时间、公平性）问题。\n6.  **模拟器 (56次)**：玩家关注**跨平台公平性**问题，可能对模拟器玩家与手机玩家同服竞技不满。\n7.  **画面 (43次)**：对**美术表现**的具体讨论，可能包含正负面评价。\n8.  **中锋 (40次) / 9. 得分后卫 (35次)**：具体**职业/角色平衡性**是讨论焦点。\n\n**解读**：玩家反馈高度集中在 **“安卓设备兼容性”**、 **“网络质量”** 和 **“付费与平衡”** 三大领域。\n\n## 6. 核心问题诊断\n基于低分样本、关键词及维度分析，提炼以下最严重问题：\n\n### 问题一：账号数据丢失与迁移问题\n- **问题描述**：大量老玩家反馈账号无法登录、数据被清除，疑似因更换服务商或合服操作导致。玩家情绪极其愤怒（“还我账号”、“垃圾”）。\n- **影响范围**：极高。直接影响核心用户留存与游戏信誉，是引发1星差评的主要原因。\n- **优先级**：**P0 - 立即处理**\n- **建议措施**：\n    1.  立即公告说明情况，诚恳道歉。\n    2.  紧急开设账号申诉与数据恢复通道。\n    3.  对确认丢失数据的玩家提供一次性高额补偿方案。\n\n### 问题二：网络延迟与连接稳定性差\n- **问题描述**：“网络延迟”是第二大高频词，严重影响实时对战游戏的核心体验，导致操作卡顿、判定失败。\n- **影响范围**：极广。所有进行在线对战的玩家均可能受影响。\n- **优先级**：**P0 - 立即处理**\n- **建议措施**：\n    1.  优化服务器架构与线路，增加BGP节点。\n    2.  在游戏内增加网络诊断工具与更明显的延迟显示。\n    3.  针对高延迟地区推出专项优化活动或补偿。\n\n### 问题三：付费设计引发“付费致强”与平衡性质疑\n- **问题描述**：“氪金”、“充值”、“平衡”关键词高频出现。玩家普遍认为游戏“充钱就厉害”，破坏了竞技公平性。\n- **影响范围**：广。严重影响游戏长期生态和中低付费玩家体验。\n- **优先级**：**P1 - 高优规划**\n- **建议措施**：\n    1.  审视付费球员/道具的属性数值，确保其在技术可弥补的范围内。\n    2.  增加通过活跃玩法获得顶级球员/资源的途径。\n    3.  加强“公平竞技”宣传，举办纯技术性赛事。\n\n### 问题四：安卓端，特别是国产机型兼容性与性能问题\n- **问题描述**：华为、小米、vivo等品牌被单独提及，表明游戏在这些主流安卓设备上存在卡顿、发热、闪退等优化问题。\n- **影响范围**：较广。安卓用户基数庞大，体验受损直接影响评分和口碑。\n- **优先级**：**P1 - 高优规划**\n- **建议措施**：\n    1.  成立专项小组，针对TOP机型进行深度适配与性能优化。\n    2.  在官网和商店页面公布推荐配置与已知问题机型。\n    3.  提供画质分级选项，允许低配设备降低特效以保证流畅度。\n\n## 7. 正面体验亮点\n- **核心战斗玩法得到认可**：“战斗体验”维度得分相对最高（54.6），是游戏的基石。玩家对篮球对战本身的过程仍有期待和一定认可。\n- **球员培养系统有深度**：高分样本（尽管内容重复）提到了“球员培养”系统，表明该系统的深度和可玩性可能被部分核心玩家所欣赏。\n- **题材与市场潜力**：篮球题材本身拥有广泛受众，玩家反馈中虽有大量批评，但也隐含了“恨铁不成钢”的期待，说明市场需求真实存在。\n\n## 8. 总结与行动建议\n按优先级排序，建议团队立即采取以下行动：\n\n1.  **【P0】成立“账号危机”应急小组**：首要任务是解决历史账号丢失问题，挽回核心用户信任，遏制口碑崩盘。\n2.  **【P0】启动“网络优化”专项攻坚**：联合技术、运维部门，从服务器、客户端、运营商合作多层面提升网络稳定性，这是留存对战玩家的生命线。\n3.  **【P1】重构付费与平衡性沟通**：短期内公布平衡性调整计划，长期需重新规划付费点，将“为爱付费”与“为强付费”分离，确保竞技公平底线。\n4.  **【P1】启动“安卓护航”优化计划**：针对主流机型进行深度性能调优，并建立玩家反馈-快速响应的机型适配通道。\n5.  **【P2】基于“战斗体验”亮点进行版本宣传**：在解决上述严重问题后，以“流畅公平的篮球竞技”为核心卖点，结合玩家认可的球员培养深度，进行口碑修复和新版本推广。\n6.  **【P2】建立常态化的玩家反馈闭环机制**：将本次分析的维度（平衡、手感、兼容等）纳入日常监控，定期发布“玩家问题回应与修复报告”，重建沟通桥梁。",
  "summary": "共 842 份反馈（questionnaire 499条、appstore 196条、taptap 147条），平均分 38.3，正面评价 32%，紧急问题 undefined 个",
  "createdAt": "2026-04-21T11:10:09.023Z"
}