{
  "period1": {
    "label": "早期数据",
    "dateRange": "",
    "totalFeedback": 3669,
    "avgScore": 27.9,
    "positiveRate": 25,
    "negativeRate": 51,
    "categoryDistribution": {
      "综合体验": 1472,
      "游戏平衡": 1274,
      "操作手感": 296,
      "美术表现": 144,
      "玩法设计": 132,
      "战斗体验": 125,
      "整体体验": 124,
      "性能问题": 95,
      "设备兼容": 7
    },
    "sentimentDistribution": {
      "positive": 25,
      "neutral": 25,
      "negative": 51
    },
    "topKeywords": [
      {
        "keyword": "氪金",
        "count": 1047
      },
      {
        "keyword": "匹配",
        "count": 588
      },
      {
        "keyword": "画面",
        "count": 455
      },
      {
        "keyword": "技能",
        "count": 362
      },
      {
        "keyword": "安卓手机",
        "count": 309
      },
      {
        "keyword": "充值",
        "count": 293
      },
      {
        "keyword": "网络延迟",
        "count": 254
      },
      {
        "keyword": "平衡",
        "count": 230
      },
      {
        "keyword": "手感",
        "count": 230
      },
      {
        "keyword": "操作",
        "count": 228
      },
      {
        "keyword": "网络",
        "count": 159
      },
      {
        "keyword": "天赋",
        "count": 97
      },
      {
        "keyword": "卡顿",
        "count": 95
      },
      {
        "keyword": "职业",
        "count": 95
      },
      {
        "keyword": "华为",
        "count": 93
      }
    ],
    "topIssues": [
      {
        "issue": "综合体验",
        "count": 1024,
        "severity": "critical"
      },
      {
        "issue": "游戏平衡",
        "count": 582,
        "severity": "critical"
      },
      {
        "issue": "操作手感",
        "count": 70,
        "severity": "medium"
      },
      {
        "issue": "玩法设计",
        "count": 70,
        "severity": "medium"
      },
      {
        "issue": "美术表现",
        "count": 53,
        "severity": "medium"
      },
      {
        "issue": "整体体验",
        "count": 48,
        "severity": "medium"
      },
      {
        "issue": "战斗体验",
        "count": 5,
        "severity": "medium"
      },
      {
        "issue": "设备兼容",
        "count": 2,
        "severity": "medium"
      }
    ]
  },
  "period2": {
    "label": "近期数据",
    "dateRange": "",
    "totalFeedback": 3669,
    "avgScore": 21.6,
    "positiveRate": 22,
    "negativeRate": 63,
    "categoryDistribution": {
      "综合体验": 1887,
      "游戏平衡": 1188,
      "操作手感": 260,
      "玩法设计": 185,
      "性能问题": 112,
      "美术表现": 37
    },
    "sentimentDistribution": {
      "positive": 22,
      "neutral": 15,
      "negative": 63
    },
    "topKeywords": [
      {
        "keyword": "氪金",
        "count": 1039
      },
      {
        "keyword": "匹配",
        "count": 666
      },
      {
        "keyword": "画面",
        "count": 519
      },
      {
        "keyword": "技能",
        "count": 407
      },
      {
        "keyword": "操作",
        "count": 335
      },
      {
        "keyword": "充值",
        "count": 260
      },
      {
        "keyword": "平衡",
        "count": 259
      },
      {
        "keyword": "手感",
        "count": 222
      },
      {
        "keyword": "网络",
        "count": 186
      },
      {
        "keyword": "职业",
        "count": 149
      },
      {
        "keyword": "卡顿",
        "count": 112
      },
      {
        "keyword": "天赋",
        "count": 75
      }
    ],
    "topIssues": [
      {
        "issue": "综合体验",
        "count": 1369,
        "severity": "critical"
      },
      {
        "issue": "游戏平衡",
        "count": 690,
        "severity": "critical"
      },
      {
        "issue": "操作手感",
        "count": 112,
        "severity": "medium"
      },
      {
        "issue": "玩法设计",
        "count": 101,
        "severity": "medium"
      },
      {
        "issue": "美术表现",
        "count": 37,
        "severity": "medium"
      }
    ]
  }
}